QCut/__init__.py
QCut/backend_utility.py
QCut/cutcircuit.py
QCut/cutlocation.py
QCut/helper.py
QCut/qcuterror.py
QCut/qcutresult.py
QCut/qpd.py
QCut/qpd_gates.py
QCut/single_qubit_wirecut.py
QCut/wirecut.py
QCut/QCutFind/__init__.py
QCut/QCutFind/combine_subcircuits.py
QCut/QCutFind/cut_finding.py
QCut/QCutFind/graph_circuit_utils.py
QCut/QCutFind/metis.py
QCut/QCutFind/refine.py
docs/Acknowledgement.rst
docs/AutomaticCuts.rst
docs/Changelog.rst
docs/Examples.rst
docs/GateCuts.rst
docs/License.rst
docs/Makefile
docs/Multiple_cuts.rst
docs/Notebooks.rst
docs/QCut.rst
docs/Usage.rst
docs/WireCuts.rst
docs/conf.py
docs/index.rst
docs/make.bat
docs/requirements-docs.txt
docs/_static/images/QCut-logo.jpg
docs/_static/images/circ1.png
docs/_static/images/circ10.png
docs/_static/images/circ11.png
docs/_static/images/circ1_old.png
docs/_static/images/circ2.png
docs/_static/images/circ2_old.png
docs/_static/images/circ3.png
docs/_static/images/circ3_old.png
docs/_static/images/circ4.png
docs/_static/images/circ4_odl.png
docs/_static/images/circ5.png
docs/_static/images/circ6.png
docs/_static/images/circ7.png
docs/_static/images/circ8.png
docs/_static/images/circ9.png
docs/examples/QCutBasicUsage.ipynb
docs/examples/QCutCutSubsequentWires.ipynb
docs/examples/QCutCutToThreeParts.ipynb
docs/examples/QCutMultipleCutsOnSingleWire.ipynb
docs/examples/QCutQAOAExample.ipynb
qcut-0.9.0.dist-info/licenses/LICENSE
qcut-0.9.0.dist-info/METADATA
qcut-0.9.0.dist-info/WHEEL
qcut-0.9.0.dist-info/top_level.txt
qcut-0.9.0.dist-info/RECORD
