Metadata-Version: 2.4
Name: QCut
Version: 0.9.0
Summary: A package for performing wire cuts of hardware without reset-gates or mid-circuit measurements. Built on top of qiskit
Author-email: Joonas Nivala <joonas.nivala@gmail.com>
License:                                  Apache License
Project-URL: homepage, https://github.com/JooNiv/QCut
Project-URL: documentation, https://jooniv.github.io/QCut/
Project-URL: repository, https://github.com/JooNiv/QCut.git
Project-URL: changelog, https://github.com/JooNiv/QCut/blob/main/CHANGELOG.rst
Classifier: Development Status :: 4 - Beta
Classifier: Programming Language :: Python :: 3 :: Only
Classifier: Topic :: Scientific/Engineering :: Physics
Classifier: Intended Audience :: Science/Research
Requires-Python: <3.13,>=3.10
License-File: LICENSE
Requires-Dist: qiskit<1.2,>=1.0
Requires-Dist: numpy
Requires-Dist: qiskit-aer<0.15,>=0.13.0
Requires-Dist: qiskit-iqm==17.8
Requires-Dist: pymetis==2025.1.1
Provides-Extra: dev
Requires-Dist: pytest; extra == "dev"
Requires-Dist: pytest-cov; extra == "dev"
Requires-Dist: ruff; extra == "dev"
Dynamic: license-file
